{
  "version": 1,
  "author": "Grupo de Alunos ADS",
  "editor": "wokwi",
  "parts": [
    {
      "type": "board-esp32-devkit-v1",
      "id": "esp32",
      "top": -60.32,
      "left": 43.2,
      "attrs": {}
    },
    {
      "type": "wokwi-hc-sr04",
      "id": "ultrasonic1",
      "top": -75.3,
      "left": -167.3,
      "attrs": { "distance": "20" }
    },
    {
      "type": "wokwi-relay-module",
      "id": "relay1",
      "top": 125,
      "left": 278.4,
      "attrs": {}
    },
    {
      "type": "wokwi-led",
      "id": "led1",
      "top": -3.6,
      "left": 416.6,
      "attrs": { "color": "red" }
    },
    {
      "type": "wokwi-resistor",
      "id": "resistor1",
      "top": 91.2,
      "left": 393.05,
      "rotate": 90,
      "attrs": { "value": "220" }
    },
    {
      "type": "wokwi-gnd",
      "id": "gnd1",
      "top": 28.8,
      "left": 373.8,
      "attrs": {}
    },
    {
      "type": "wokwi-vcc",
      "id": "vcc1",
      "top": 106.36,
      "left": 451.2,
      "attrs": {}
    }
  ],
  "connections": [
    ["esp32:TX0", "$serialMonitor:RX", "", []],
    ["esp32:RX0", "$serialMonitor:TX", "", []],
    ["ultrasonic1:TRIG", "esp32:D5", "orange", []],
    ["ultrasonic1:ECHO", "esp32:D18", "green", []],
    ["ultrasonic1:VCC", "esp32:5V", "red", []],
    ["ultrasonic1:GND", "esp32:GND.2", "black", []],
    ["relay1:VCC", "esp32:5V", "red", []],
    ["relay1:GND", "esp32:GND.2", "black", []],
    ["relay1:IN", "esp32:D23", "blue", []],
    ["led1:A", "resistor1:1", "red", []],
    ["resistor1:2", "esp32:D23", "red", []],
    ["led1:C", "esp32:GND.3", "black", []],
    ["vcc1:VCC", "relay1:NO", "red", []]
  ]
}
